migri/__init__.py
migri/elements.py
migri/interfaces.py
migri/main.py
migri/migration.py
migri/utils.py
migri/backends/__init__.py
migri/backends/mysql.py
migri/backends/postgresql.py
migri/backends/sqlite.py
migri/sql/default_applied_migration.sql
migri/sql/mysql_applied_migration.sql
test/__init__.py
test/conftest.py
test/constants.py
test/test_interfaces.py
test/aiomysql/__init__.py
test/aiomysql/conftest.py
test/aiomysql/fixtures.py
test/aiomysql/test_apply_migrations.py
test/aiomysql/test_mysql.py
test/aiosqlite/__init__.py
test/aiosqlite/fixtures.py
test/aiosqlite/test_apply_migrations.py
test/aiosqlite/test_sqlite.py
test/asyncpg/__init__.py
test/asyncpg/conftest.py
test/asyncpg/fixtures.py
test/asyncpg/test_apply_migrations.py
test/asyncpg/test_postgresql.py
test/integration/__init__.py
test/integration/conftest.py
test/integration/test_migrate.py
migri-0.7.0.dist-info/LICENSE
migri-0.7.0.dist-info/METADATA
migri-0.7.0.dist-info/WHEEL
migri-0.7.0.dist-info/entry_points.txt
migri-0.7.0.dist-info/top_level.txt
migri-0.7.0.dist-info/RECORD
