Metadata-Version: 2.1
Name: migri
Version: 0.7.0
Summary: UNKNOWN
Home-page: https://github.com/RonquilloAeon/migri
License: UNKNOWN
Platform: UNKNOWN
Classifier: Development Status :: 3 - Alpha
Classifier: Environment :: Console
Classifier: Intended Audience :: Developers
Classifier: License :: OSI Approved :: MIT License
Classifier: Programming Language :: Python :: 3.7
Classifier: Programming Language :: Python :: 3.8
Classifier: Programming Language :: Python :: 3.9
Classifier: Programming Language :: Python :: 3.10
Classifier: Topic :: Database
Requires-Python: <3.11,>=3.7
License-File: LICENSE
Requires-Dist: asyncpg
Requires-Dist: click (<9,>=7)
Requires-Dist: sqlparse (==0.4.*)
Provides-Extra: mysql
Requires-Dist: aiomysql ; extra == 'mysql'
Provides-Extra: postgresql
Requires-Dist: asyncpg ; extra == 'postgresql'
Provides-Extra: sqlite
Requires-Dist: aiosqlite ; extra == 'sqlite'
